[
	{
		"squad_name": "SQUAD 1",
		"function": "OD",
		"squad": ["Kenneth", "Koharu Usui", "Mai Phan", "Beverley Musaka", "Med Amine Ghariani", "Melissa Guillen", "Tamila Kholmatova", "Maysoon Al-Attar", "Laura Ivić", "Rakshith Srinivasan", "Patrick Bugno", "Freddy Alejandro Fernández Córdova", "Azmi Abroug"],
		"link": "https://t.me/+scgxO8TKD4E0MGU1"
	},
	{
		"squad_name": "SQUAD 2",
		"function": "OD",
		"squad": ["Şevval", "Hanin Nsiri", "Aurora Dalla Torre", "Yağmur Saldanlı", "Haruki Shirai", "Nana Frimpong Opoku", "Yilin WANG", "Hoi Tung Tsang", "Karthik Ramanathan", "Manuel Mabote", "Muhamed Essam", "Luka Zečev", "Simon-Tolga Sambale"],
		"link": "https://t.me/+7XlsYYxIyXhjMGY1"
	},
	{
		"squad_name": "SQUAD 3",
		"function": "OD",
		"squad": ["Jéssica","Lucie Caillat", "Wissal Kader", "Daniel Ciura", "Ryo Suzuki", "Yapi Marcel Oholiab Kouadio", "Dyon De Hoedt", "Nehal Mohamed", "Bettina Marlise Rae Quilapio", "Theresa Kranner", "Johan Cubong", "Aakkash Gnanaretnam", "Luke von Glasow"],
		"link": "https://t.me/+iyruzrUd2L1kYWVl"
	},
	{
		"squad_name": "SQUAD 4",
		"function": "OD",
		"squad": ["Rukevwe","Yuya Takahashi", "Dušan Milošević", "Emre Eker", "Djordje Djorovic", "Avandithlakan Ravi", "Dhruv Kothari", "Noor Mahmood", "Jenny Yen", "Middii Bayer", "Lisa Brüning", "Ying Qiao Lee", "Cynthia Wachira"],
		"link": "https://t.me/+95JLRIq_MaI2MjVl"
	},
	{
		"squad_name": "SQUAD 5",
		"function": "Finance",
		"squad": ["Lucia","Katrin Penker", "Aleksander Kowalczewski", "Min Syuan Zeng", "Muthoni Kamau", "Kuan Yu Chen", "Sam Williamson", "Antonia Mandić", "Temitope Bernard", "Diego Mireles", "Samar Jeddi", "Muthu Palaniappan Ramanathan", "Minol Jayakody"],
		"link": "https://t.me/+8tALCOvmPzwyYWY1"
	},
	{
		"squad_name": "SQUAD 6",
		"function": "Finance",
		"squad": ["Paras Panwar","Michelle Chong", "Houston Hoang", "Nicolaas Haarsma", "Kacper Jaworski", "Ivana Jelenković", "Su Ha Hwang", "Lauryne Maghanga", "Ishwari Rakshe", "Henry Tran", "Tarek Al-Mosa", "Nandesh Goudar", "Recep Çağlar Mazlum"],
		"link": "https://t.me/+DXIWcvxvsmQ4NWZl"
	},
	{
		"squad_name": "SQUAD 7",
		"function": "Finance",
		"squad": ["Vy","Yaren Demir", "Serafima Sedyakina", "rendynothe yuranda", "Myadagaa Dogsom", "Kazım Emre Aydıngülü", "İpek Öztüfekçi", "Marta Radovanovic", "ZETA GEORGARI", "Taiki Yamazoe", "Michelle Mutevu", "Sandra Maina", "Long Ching Yuan"],
		"link": "https://t.me/+QlmWPEOKGxQzNDJl"
	},
	{
		"squad_name": "SQUAD 9",
		"function": "Membership",
		"squad": ["Marta Lourdes","Liya Veranchuk", "Cheuk Kiu Ng", "Tiisetso Mokete", "Alejandra Cervantes Monter", "Selene Shen", "Izza Ikhlaq Malik", "Ahmed Ellithy", "Tamilla Gambarova", "Hana Engida", "Eray Duman", "Laura Ruiz", "Yu Wun Chan", "William Chang"],
		"link": "https://t.me/+QAlcIFhvhho0ZDU9"
	},
	{
		"squad_name": "SQUAD 10",
		"function": "Membership",
		"squad": ["Paulina Gutiérrez Ávila","Ho Ching Ting", "Uthpalani Jayasinghe", "Jantsankhorloo Tseveendorj", "Anita Westfalewski", "Naadiya Khulusie", "Aïcha Ndong", "Duc Anh Le Hoang", "Coralia Magheran", "Rhona Mukami", "Dhruv Naidu", "Yevheniia Denysievska", "Vu Thi Hong Chau"],
		"link": "https://t.me/+lnJaHOl0EJc4OGI1"
	},
	{
		"squad_name": "SQUAD 11",
		"function": "Membership",
		"squad": ["Oğuzhan AYTAER","Yap Xing Yi", "Ayaka Oba", "Adrien Coudray-Kossonogow", "Márk Reszter", "Mahnoor Yazdani", "Brandon Giang", "Ahmed Nadzry Azli", "Malak Nader", "Lina Poveda", "Makeba Idah", "Liheng Phe", "Petra Zlatković"],
		"link": "https://t.me/+sbGL7-u_sfYwYzk1"
	},
	{
		"squad_name": "SQUAD 12",
		"function": "Brand/MKT",
		"squad": ["Davide","Michaela Hrušková", "Tisal Rathnayake", "Annie Yang", "SAIFALLAH KRIDANE", "Ivana Stevanovic", "ASTON MBOTO", "Husam Sawafta", "Hala Alkharabsheh", "Yulisa Camacho Delgado", "Francesco Urraro", "Gianluca Albano Silva", "Yu Okabayashi"],
		"link": "https://t.me/+MtjiO0tODaxlYTU1"
	},
	{
		"squad_name": "SQUAD 13",
		"function": "Brand/MKT",
		"squad": ["Mercy Jacob","Dafne Sagrati", "Maragatha Valli", "Reem Alaa", "Zachary Younger", "Gantogtokh Tumenjargal", "Rana Baibars", "Pramin Krajanglikit", "Giada Gulotta", "Felix Dosu", "Georgia Johnson", "Maria Badie", "Vicky Mugo"],
		"link": "https://t.me/+8NjB-42DjFxjYTA1"
	},
	{
		"squad_name": "SQUAD 14",
		"function": "Operations/Exchanges",
		"squad": ["Omar Abd El-Aziz","Mariia Serhiichuk", "Arianna Maschio", "Beril Kübra ÖZ", "Chamuditha Guruge", "Dunithi Leuwanduwa", "Mohamed Yassine Nacef", "Portia Torigoe", "Thenuri Gajaweera", "Mohamed Bechir Lahouar", "Juan Pablo Gomez", "Emre Tatar", "Sonela Ahmetaj"],
		"link": "https://t.me/+vdA9cv1pPUc3MjA1"
	},
	{
		"squad_name": "SQUAD 15",
		"function": "Operations/Exchanges",
		"squad": ["Isidora","Karin Švorcová", "Baran Büyükaslan", "Ömer Faruk Akay", "Perion Lim", "Senuri Chathurangi", "Dinna Daniel Laizer", "David Duda", "Fawaz Mohammed", "Danmar Chavez", "Cindy Bajracharya", "Mohamed Aziz Becher", "Sarah Bohner"],
		"link": "https://t.me/+naQTDi-T6ylhZjQ0"
	},
	{
		"squad_name": "SQUAD 16",
		"function": "Operations/Exchanges",
		"squad": ["Chan Yun Him Anson","Jana Opherden", "Lejla Nuhić", "Menna Alaa", "Prabashi Wanigasinghe", "Shi Nam Woo", "Mohamed Aladraj", "Vini Vijayakumar", "Ali Badreddine", "Jiya Ashar", "Juan David Ospina Díaz", "Şevval Orak", "Shubham Ganguly"],
		"link": "https://t.me/+_wrMWDVe2IQ1YzBk"
	},
	{
		"squad_name": "SQUAD 17",
		"function": "Operations/Exchanges",
		"squad": ["Juan Pablo Abaúnza","Hannah Kasmani", "Angelina Gryshyk", "Ruby Chuang", "Yifei Zhang", "Márton Somkuti", "Laura Covre", "Daniel Arturo Aisa Castro", "Hanna Loika", "Akrout Yosr", "Gustavo de Mello", "Yazan Youssef", "Aquila P A Gargli"],
		"link": "https://t.me/+ehRUd3BwYb8xZmRk"
	},
	{
		"squad_name": "SQUAD 18",
		"function": "Operations/Exchanges",
		"squad": ["Hussain Almusawi","Cemre Karbuz", "Dan Lozano", "Shinya Shimizu", "Sanuthi Weerasena", "Youssef Sharaf", "Francesca Villano", "Enkhmurun Monkhor", "Čeda Veličković", "Lynn Ghosn", "Jose Galindo", "Nijat Tahirli", "Abdoulaye SANOU"],
		"link": "https://t.me/+v_ut2NUL0lIzNTU0"
	},
	{
		"squad_name": "SQUAD 19",
		"function": "Operations/Exchanges",
		"squad": ["Vikum Wijekoon","Sıla Kızılyurt", "Ana Carolina Cosenza", "Anastasiia Shykera", "Mariam Alswaf", "Taher Mohamed", "Lisette Eliud Garcia Ramirez", "Angelina Vaikhel", "Samira Hallal", "Kentaro Kato", "Fouzul Hassan", "Nijat Tahirli", "Abdoulaye SANOU"],
		"link": "https://t.me/+XOrqklrqbYljNzVk"
	},
	{
		"squad_name": "SQUAD 20",
		"function": "Operations/Exchanges",
		"squad": ["Sajana","Fatih Mert Deniz", "Iva Radakovic", "Man Shum", "Anastasia Pleshakova", "Youssef Mohamed", "Eduardo Mattos Lima da Cruz", "Haoze Li", "Mohammad Abdul Wasay", "Hanifah Nakalubi", "Maximiliano Najera Becerra", "Sadeesha Sathmina", "Asbin Khanal"],
		"link": "https://t.me/+I28TRFCan24zNzE0"
	},
	{
		"squad_name": "SQUAD 21",
		"function": "Operations/Exchanges",
		"squad": ["Leo","Emre Tatar", "Sonela Ahmetaj", "Alexandra Jose", "Kao Hua", "Kathleen Callista Widyantara", "Anastasiia Puhach", "Angelo Ansel Coronel", "XINYI QIU", "Abdoulaye SANOU", "oumayma guesmi", "Yuetong Xiong", "Andrea Wiesinger"],
		"link": "https://t.me/+fEVdDgsLZ9NjZTdk"
	},
	{
		"squad_name": "SQUAD 22",
		"function": "Operations/Exchanges",
		"squad": ["Reneta Biglieri","Liza Kravchenko", "Reneta Biglieri", "Ayesh Rajapaksha", "Parth Shukla", "Mohamed Hassan", "Hsin Yi Ma", "Hasan Alhussainy", "Dániel Szentesi", "Trizah Mudambo", "Cuauhtli Yetuani Curiel Padilla", "Seth Mbasha", "Lamia Alwir", "Lisa Brüning"],
		"link": "https://t.me/+IRg537H9qDU2NWE0"
	},
	{
		"squad_name": "SQUAD 23",
		"function": "BD",
		"squad": ["Thao (BoBo)", "Thao", "Bobo", "Roxana Ruiz Murcia", "Bobo Aleyna", "Alyona Yuryeva", "S GOKULA KRISHNA", "Chin Tung Chantel Chan", "Firas Atigui", "Hermela sisay Engida", "Jeremy Prawira", "Modiedie Trevor Molelemane", "Bülent Ayın", "Sara Houria", "Irene Yang", "Yeva Asatryan"],
		"link": "https://t.me/+2edKuTSF-o9hOTBk"
	},
	{
		"squad_name": "SQUAD 24",
		"function": "BD",
		"squad": ["Anastasiia Puhach", "Maike von Hofmann", "Anastasiia Puhach Sansali", "Leonardo Oliveira", "Louai Belfounes", "Farah Elashry", "Jimena Tintinago", "Darsh Asera", "Houssem Krebazza", "LINGXI HU", "Shees Khalid", "Saleh Ladgham", "Mifid ADOYI GADO", "Lovro Cvjetković"],
		"link": "https://t.me/+rS2WZIR-k_oyYTc0"
	},
	{
		"squad_name": "SQUAD 25",
		"function": "BD",
		"squad": ["Arfan", "Irene Martín Martín", "Arfan Leysan", "Daiki Moriguchi", "Maria Cecilia Mendiola", "Maya Ghazy", "Marc Velasco Garcia", "Muhammad Shayan Raza", "Joseph Olagbaju", "Andrija Vasić", "Adel Rajhi", "Shreenidhi Suresh", "Puhach Anastasiia", "Angelo Ansel Coronel"],
		"link": "https://t.me/+SXV9fBTlssZlMmE8"
	},
	{
		"squad_name": "SQUAD 26",
		"function": "Virtual Squad",
		"squad": ["Yan", "Rawan Alshammari", "Andrea Chumacero Carballo", "Danilo Martins", "Iris SASTRE", "Abigail Garro", "RODINA ELDALY", "Borhen Adaly", "Aditi Yerne", "Mohalla Burhaniwala", "Tadiwanashe Mkonto", "Eya Achour", "Nana Frimpong Opoku"],
		"link": "https://t.me/+xN_8Xj7Ab1s4NjVl"
	},
	{
		"squad_name": "SQUAD 27",
		"function": "Virtual Squad",
		"squad": ["Rita Costa Moreira", "Samira Hallal", "Yosr Braham", "Shyamal de silva", "Lohodedoo Yakubu Ishima", "Camila Bermudez Zabala", "Maria Auleria", "David Pulido Rozo", "Tadiwanashe Mkonto", "Nitin Prakash", "Lennert Jessen", "mohamed jemili", "Eunhakkee"],
		"link": "https://t.me/+nlUugW9kvzgxNDBl"
	},
	{
		"squad_name": "SQUAD 28",
		"function": "Virtual Squad",
		"squad": ["Eugene", "Thomas Sardauna", "Izza Ikhlaq", "Mohamed hassan adam", "Samuel Ogundipe", "Zachary Younger", "Jennifer Tesalonika Erick", "Zhan Kudaibergenov", "Alina Tanveer", "Nijat Ahmadov", "Dinal Majitha Dias", "Sofya", "Joy Martha Kari Kiberu"],
		"link": "https://t.me/+u9KoR-872RFlZDI1"
	},
	{
		"squad_name": "SQUAD 29",
		"function": "Virtual Squad",
		"squad": ["Kaneel","Nour Salama", "Qudus Ajibade Adeyemi", "Bogdan-Lucian Gabor", "Lina Rechid", "Anna Katalin Oláh", "Sebastian Pinzon", "Khushi shrivastava", "Aïcha Ndong", "Daniela Michelle", "Aditya Poddar"],
		"link": "https://t.me/+_qtdzox8B801ZTI1"
	},
	{
		"squad_name": "SQUAD 30",
		"function": "Virtual Squad",
		"squad": ["Kezban TAŞ","MOATASSIM Alae", "Sonia Dorofieieva", "Jannie Lee", "Zahra Hizra", "Sunag kp", "preeti kafle", "Aaditya Gupta", "Kesalya Karunanayake", "VO THANH NHAN", "Shaima Iyad Sameer Kloub", "Mohamed Allam", "Eleonora Pezzi"],
		"link": "https://t.me/+IUgvXCAfD3tkODU9"
	}
]